pip_services4_grpc/__init__.py
pip_services4_grpc/build/DefaultGrpcFactory.py
pip_services4_grpc/build/__init__.py
pip_services4_grpc/clients/CommandableGrpcClient.py
pip_services4_grpc/clients/GrpcClient.py
pip_services4_grpc/clients/__init__.py
pip_services4_grpc/controllers/CommandableGrpcController.py
pip_services4_grpc/controllers/GrpcController.py
pip_services4_grpc/controllers/GrpcEndpoint.py
pip_services4_grpc/controllers/IRegisterable.py
pip_services4_grpc/controllers/__init__.py
pip_services4_grpc/protos/__init__.py
pip_services4_grpc/protos/commandable_pb2.py
pip_services4_grpc/protos/commandable_pb2_grpc.py
pip_services4_grpc/test/TestCommandableGrpcClient.py
pip_services4_grpc/test/TestGrpcClient.py
pip_services4_grpc/test/__init__.py
pip_services4_grpc-0.0.2.dist-info/METADATA
pip_services4_grpc-0.0.2.dist-info/WHEEL
pip_services4_grpc-0.0.2.dist-info/top_level.txt
pip_services4_grpc-0.0.2.dist-info/zip-safe
pip_services4_grpc-0.0.2.dist-info/RECORD
