Metadata-Version: 2.1
Name: pip_services4_grpc
Version: 0.0.2
Summary: gRPC clients and controllers for Pip.Services in Python
Home-page: http://github.com/pip-services4/pip-services4-python/tree/main/tree/main//pip-services4-grpc-python
Author: Conceptual Vision Consulting LLC
Author-email: seroukhov@gmail.com
License: MIT
Platform: any
Classifier: Development Status :: 4 - Beta
Classifier: Intended Audience :: Developers
Classifier: License :: OSI Approved :: MIT License
Classifier: Operating System :: OS Independent
Classifier: Programming Language :: Python
Classifier: Programming Language :: Python :: 3.6
Classifier: Programming Language :: Python :: 3.7
Classifier: Programming Language :: Python :: 3.8
Classifier: Topic :: Software Development :: Libraries :: Python Modules
Requires-Dist: grpcio <2.0.0,>=1.43.0
Requires-Dist: grpcio-tools <2.0.0,>=1.43.0
Requires-Dist: protobuf <6.0.0,>=3.19.3
Requires-Dist: pip-services4-commons <1.0,>=0.0.1
Requires-Dist: pip-services4-rpc <1.0,>=0.0.1
Requires-Dist: pip-services4-components <1.0,>=0.0.1
